quepasa/__init__.py
quepasa/api_client.py
quepasa/api_response.py
quepasa/configuration.py
quepasa/exceptions.py
quepasa/py.typed
quepasa/rest.py
quepasa/api/__init__.py
quepasa/api/default_api.py
quepasa/models/__init__.py
quepasa/models/answer_detail.py
quepasa/models/answer_detail_data.py
quepasa/models/answer_detail_data_labeled_links_value.py
quepasa/models/answer_detail_data_links_value.py
quepasa/models/batch_status.py
quepasa/models/batch_status_data.py
quepasa/models/chunks_detail.py
quepasa/models/chunks_detail_data_inner.py
quepasa/models/created_batch_status.py
quepasa/models/created_batch_status_data.py
quepasa/models/document.py
quepasa/models/document_detail.py
quepasa/models/document_detail_data.py
quepasa/models/document_detail_data_pages_inner.py
quepasa/models/document_not_found.py
quepasa/models/document_pages_inner.py
quepasa/models/domain_data_detail.py
quepasa/models/domain_detail.py
quepasa/models/domain_list_detail.py
quepasa/models/operation_failed_status.py
quepasa/models/retrieve_answer_request.py
quepasa/models/retrieve_answer_request_document_relevance_weights.py
quepasa/models/retrieve_answer_request_relevance_weights.py
quepasa/models/retrieve_answer_request_user_info.py
quepasa/models/retrieve_chunks_request.py
quepasa/models/setup_telegram_request.py
quepasa/models/setup_telegram_request_commands.py
quepasa/models/setup_telegram_request_commands_ask.py
quepasa/models/setup_telegram_request_commands_start.py
quepasa/models/telegram_status.py
quepasa-1.0.4.dist-info/METADATA
quepasa-1.0.4.dist-info/WHEEL
quepasa-1.0.4.dist-info/top_level.txt
quepasa-1.0.4.dist-info/RECORD
