Metadata-Version: 2.1
Name: quepasa
Version: 1.0.4
Summary: QuePasa RAG SaaS API
Home-page: https://docs.quepasa.ai/
Author: Quepasa.ai
Author-email: yuri@quepasa.ai
License: UNKNOWN
Keywords: QuePasa RAG SaaS API
Platform: UNKNOWN
Requires-Dist: urllib3 (<2.1.0,>=1.25.3)
Requires-Dist: python-dateutil
Requires-Dist: pydantic (>=2)
Requires-Dist: typing-extensions (>=4.7.1)
